MANIFEST.in
requirements.txt
setup.py
echobox/__init__.py
echobox.egg-info/PKG-INFO
echobox.egg-info/SOURCES.txt
echobox.egg-info/dependency_links.txt
echobox.egg-info/requires.txt
echobox.egg-info/top_level.txt
echobox/app/__init__.py
echobox/app/appconfig.py
echobox/app/devops.py
echobox/app/env.py
echobox/app/eventlog.py
echobox/app/multiuser.py
echobox/clis/__init__.py
echobox/clis/mysqlcli.py
echobox/clis/pipcli.py
echobox/clis/rediscli.py
echobox/tool/__init__.py
echobox/tool/aliyunoss.py
echobox/tool/array.py
echobox/tool/byte.py
echobox/tool/cache.py
echobox/tool/concurrent.py
echobox/tool/conda.py
echobox/tool/crontab.py
echobox/tool/datatypes.py
echobox/tool/dockerutil.py
echobox/tool/file.py
echobox/tool/firewall.py
echobox/tool/functocli.py
echobox/tool/http.py
echobox/tool/local_cache.py
echobox/tool/logger.py
echobox/tool/net.py
echobox/tool/redistool.py
echobox/tool/spec.py
echobox/tool/ssl.py
echobox/tool/strings.py
echobox/tool/strjson.py
echobox/tool/system.py
echobox/tool/systemd.py
echobox/tool/template.py
echobox/tool/testutils.py
echobox/tool/timeutil.py
echobox/tool/utils.py
tests/__init__.py
tests/test_array.py
tests/test_concurrent.py
tests/test_dockerutil.py
tests/test_eventlog.py
tests/test_file.py
tests/test_functocli.py
tests/test_nameiddict.py
tests/test_net.py
tests/test_strings.py
tests/test_system.py
tests/test_template.py
tests/test_threadpool.py
tests/test_timer.py
tests/test_tool_cache.py
tests/test_tool_redis.py
tests/test_utils.py